fast_sentence_tokenize/__init__.py
fast_sentence_tokenize/bp/__init__.py
fast_sentence_tokenize/bp/ngrams.py
fast_sentence_tokenize/bp/tokenizer.py
fast_sentence_tokenize/dmo/__init__.py
fast_sentence_tokenize/dmo/dictionary_finder.py
fast_sentence_tokenize/dmo/pronoun_finder.py
fast_sentence_tokenize/dmo/stopword_finder.py
fast_sentence_tokenize/dto/__init__.py
fast_sentence_tokenize/dto/abbreviations_kb.py
fast_sentence_tokenize/dto/currency_kb.py
fast_sentence_tokenize/dto/dquotes_kb.py
fast_sentence_tokenize/dto/enclictics.py
fast_sentence_tokenize/dto/hyphens_kb.py
fast_sentence_tokenize/dto/squotes_kb.py
fast_sentence_tokenize/dto/stopwords_kb.py
fast_sentence_tokenize/svc/__init__.py
fast_sentence_tokenize/svc/sliding_window_extract.py
fast_sentence_tokenize/svc/tokenize_use_graffl.py
fast_sentence_tokenize/svc/tokenize_use_spacy.py
fast_sentence_tokenize-0.1.15.dist-info/METADATA
fast_sentence_tokenize-0.1.15.dist-info/WHEEL
fast_sentence_tokenize-0.1.15.dist-info/RECORD
